src/EcmaTimer.py
src/__init__.py
src/__main__.py
EcmaTimer-1.0.0.dist-info/METADATA
EcmaTimer-1.0.0.dist-info/WHEEL
EcmaTimer-1.0.0.dist-info/entry_points.txt
EcmaTimer-1.0.0.dist-info/top_level.txt
EcmaTimer-1.0.0.dist-info/RECORD
