Metadata-Version: 2.2
Name: EcmaTimer
Version: 1.0.0
Summary: An advanced timer library for managing scheduled tasks in Python.
Home-page: https://github.com/inject3r/EcmaTimer
Author: Abolfazl Hosseini
Author-email: tryuzr@gmail.com
Classifier: Programming Language :: Python :: 3
Classifier: License :: OSI Approved :: MIT License
Classifier: Operating System :: OS Independent
Requires-Python: >=3.6
Requires-Dist: asyncio
Dynamic: author
Dynamic: author-email
Dynamic: classifier
Dynamic: description
Dynamic: description-content-type
Dynamic: home-page
Dynamic: requires-dist
Dynamic: requires-python
Dynamic: summary
